{
    "title": "有斐閣法律用語辞典 第５版",
    "author": "Caoimhe",
    "url": "https://monokakido.jp/ja/dictionaries/ydl",
    "description": "本辞典は、平成五年に初版が刊行され、平成一二年に第2版、平成一八年に第3版、平成二四年に第4版と改訂を重ねてきました。最後の改訂から八年が経過し、この間、民法（債権関係、相続関係等）や刑事訴訟法といった基本法分野での大幅な法改正や、いわゆる平和安全法制の整備（自衛隊法の改正等）をはじめとする各法分野での重要な法改正があり、また、天皇の退位等に関する皇室典範特例法、行政手続における特定の個人を識別するための番号の利用等に関する法律（いわゆるマイナンバー法）、行政不服審査法、特定秘密の保護に関する法律等といった新たな法律の制定がされるなどしたことから、本辞典の内容をアップ・トゥ・デートなものとするため、第5版を刊行することとしました。",
    "attribution": "© Yuhikaku, 2022",
    "format": 3,
    "revision": "ydl;2025-04-22"
}